napari_geoscience_viewer/__init__.py
napari_geoscience_viewer/napari.yaml
napari_geoscience_viewer/quick_hdf5_netcdf_viewer.py
napari_geoscience_viewer/_tests/__init__.py
napari_geoscience_viewer/_tests/test_quick_hdf5_netcdf_viewer.py
napari_geoscience_viewer-0.1.1.dist-info/LICENSE
napari_geoscience_viewer-0.1.1.dist-info/METADATA
napari_geoscience_viewer-0.1.1.dist-info/WHEEL
napari_geoscience_viewer-0.1.1.dist-info/entry_points.txt
napari_geoscience_viewer-0.1.1.dist-info/top_level.txt
napari_geoscience_viewer-0.1.1.dist-info/RECORD
